{
  "1.1_cherg": {
    "one_1": "Немає інформації",
    "two_1": "Немає інформації",
    "three_1": "22:30-00:00",
    "four_1": "Немає інформації",
    "five_1": "Немає інформації",
    "six_1": "Немає інформації",
    "seven_1": "Немає інформації"
  },
  "1.2_cherg": {
    "one_1": "Немає інформації",
    "two_1": "Немає інформації",
    "three_1": "22:30-00:00",
    "four_1": "Немає інформації",
    "five_1": "Немає інформації",
    "six_1": "Немає інформації",
    "seven_1": "Немає інформації"
  },
  "2.1_cherg": {
    "one_1": "Немає інформації",
    "two_1": "Немає інформації",
    "three_1": "12:00-14:30",
    "four_1": "Немає інформації",
    "five_1": "Немає інформації",
    "six_1": "Немає інформації",
    "seven_1": "Немає інформації"
  },
  "2.2_cherg": {
    "one_1": "Немає інформації",
    "two_1": "Немає інформації",
    "three_1": "12:00-14:30",
    "four_1": "Немає інформації",
    "five_1": "Немає інформації",
    "six_1": "Немає інформації",
    "seven_1": "Немає інформації"
  },
  "3.1_cherg": {
    "one_1": "Немає інформації",
    "two_1": "Немає інформації",
    "three_1": "Без відключень",
    "four_1": "Немає інформації",
    "five_1": "Немає інформації",
    "six_1": "Немає інформації",
    "seven_1": "Немає інформації"
  },
  "3.2_cherg": {
    "one_1": "Немає інформації",
    "two_1": "Немає інформації",
    "three_1": "Без відключень",
    "four_1": "Немає інформації",
    "five_1": "Немає інформації",
    "six_1": "Немає інформації",
    "seven_1": "Немає інформації"
  },
  "4.1_cherg": {
    "one_1": "Немає інформації",
    "two_1": "Немає інформації",
    "three_1": "15:30-18:00",
    "four_1": "Немає інформації",
    "five_1": "Немає інформації",
    "six_1": "Немає інформації",
    "seven_1": "Немає інформації"
  },
  "4.2_cherg": {
    "one_1": "Немає інформації",
    "two_1": "Немає інформації",
    "three_1": "15:30-18:00",
    "four_1": "Немає інформації",
    "five_1": "Немає інформації",
    "six_1": "Немає інформації",
    "seven_1": "Немає інформації"
  },
  "5.1_cherg": {
    "one_1": "Немає інформації",
    "two_1": "Немає інформації",
    "three_1": "10:00-11:00",
    "four_1": "Немає інформації",
    "five_1": "Немає інформації",
    "six_1": "Немає інформації",
    "seven_1": "Немає інформації"
  },
  "5.2_cherg": {
    "one_1": "Немає інформації",
    "two_1": "Немає інформації",
    "three_1": "10:00-11:00",
    "four_1": "Немає інформації",
    "five_1": "Немає інформації",
    "six_1": "Немає інформації",
    "seven_1": "Немає інформації"
  },
  "6.1_cherg": {
    "one_1": "Немає інформації",
    "two_1": "Немає інформації",
    "three_1": "19:00-21:30",
    "four_1": "Немає інформації",
    "five_1": "Немає інформації",
    "six_1": "Немає інформації",
    "seven_1": "Немає інформації"
  },
  "6.2_cherg": {
    "one_1": "Немає інформації",
    "two_1": "Немає інформації",
    "three_1": "19:00-21:30",
    "four_1": "Немає інформації",
    "five_1": "Немає інформації",
    "six_1": "Немає інформації",
    "seven_1": "Немає інформації"
  },
  "1_cherg": {
    "one_1": "Оберіть чергу",
    "two_1": "Оберіть чергу",
    "three_1": "Оберіть чергу",
    "four_1": "Оберіть чергу",
    "five_1": "Оберіть чергу",
    "six_1": "Оберіть чергу",
    "seven_1": "Оберіть чергу"
  },
  "2_cherg": {
    "one_1": "Оберіть чергу",
    "two_1": "Оберіть чергу",
    "three_1": "Оберіть чергу",
    "four_1": "Оберіть чергу",
    "five_1": "Оберіть чергу",
    "six_1": "Оберіть чергу",
    "seven_1": "Оберіть чергу"
  },
  "3_cherg": {
    "one_1": "Оберіть чергу",
    "two_1": "Оберіть чергу",
    "three_1": "Оберіть чергу",
    "four_1": "Оберіть чергу",
    "five_1": "Оберіть чергу",
    "six_1": "Оберіть чергу",
    "seven_1": "Оберіть чергу"
  },
  "4_cherg": {
    "one_1": "Оберіть чергу",
    "two_1": "Оберіть чергу",
    "three_1": "Оберіть чергу",
    "four_1": "Оберіть чергу",
    "five_1": "Оберіть чергу",
    "six_1": "Оберіть чергу",
    "seven_1": "Оберіть чергу"
  },
  "5_cherg": {
    "one_1": "Оберіть чергу",
    "two_1": "Оберіть чергу",
    "three_1": "Оберіть чергу",
    "four_1": "Оберіть чергу",
    "five_1": "Оберіть чергу",
    "six_1": "Оберіть чергу",
    "seven_1": "Оберіть чергу"
  },
  "6_cherg": {
    "one_1": "Оберіть чергу",
    "two_1": "Оберіть чергу",
    "three_1": "Оберіть чергу",
    "four_1": "Оберіть чергу",
    "five_1": "Оберіть чергу",
    "six_1": "Оберіть чергу",
    "seven_1": "Оберіть чергу"
  },
  "database": 2,
  "source": "github",
  "mono": "3",
  "telegram": "1",
  "ad": "banner",
  "update_time": "27 жовтня о 09:50"
}
